[
    {
        "training_iteration": 1,
        "date": "2024-06-03 15:01:12",
        "execution_time_seconds": 233.610163,
        "CO2_emissions_kg": 0.011302530531983199
    },
    {
        "training_iteration": 2,
        "date": "2024-06-03 15:20:43",
        "execution_time_seconds": 247.529782,
        "CO2_emissions_kg": 0.005671969905139468
    },
    {
        "training_iteration": 3,
        "date": "2024-06-03 15:29:55",
        "execution_time_seconds": 243.16488,
        "CO2_emissions_kg": 0.009790166973912856
    },
    {
        "training_iteration": 4,
        "date": "2024-06-03 15:34:32",
        "execution_time_seconds": 239.44367,
        "CO2_emissions_kg": 0.012478961736750983
    },
    {
        "training_iteration": 5,
        "date": "2024-06-03 15:40:33",
        "execution_time_seconds": 248.360381,
        "CO2_emissions_kg": 0.01568333734439011
    },
    {
        "training_iteration": 6,
        "date": "2024-06-03 15:58:19",
        "execution_time_seconds": 250.332239,
        "CO2_emissions_kg": 0.022545958247522285
    },
    {
        "training_iteration": 7,
        "date": "2024-06-03 16:08:03",
        "execution_time_seconds": 248.718157,
        "CO2_emissions_kg": 0.0025911238922327667
    },
    {
        "training_iteration": 8,
        "date": "2024-06-03 16:14:16",
        "execution_time_seconds": 257.336122,
        "CO2_emissions_kg": 0.0026408984817699052
    },
    {
        "training_iteration": 9,
        "date": "2024-06-03 16:21:43",
        "execution_time_seconds": 262.058737,
        "CO2_emissions_kg": 0.0031687758114991938
    }
]